resp3.py
resp3-0.1.0.dist-info/LICENSE
resp3-0.1.0.dist-info/WHEEL
resp3-0.1.0.dist-info/METADATA
resp3-0.1.0.dist-info/RECORD
