Metadata-Version: 2.1
Name: resp3
Version: 0.1.0
Summary: A python implementation of RESP3.
Author: laixintao
Author-email: laixintaoo@gmail.com
Requires-Python: >=3.7,<4.0
Classifier: Programming Language :: Python :: 3
Classifier: Programming Language :: Python :: 3.7
Classifier: Programming Language :: Python :: 3.8
